thermocouples/__init__.py
thermocouples/base.py
thermocouples/py.typed
thermocouples/registry.py
thermocouples/types/__init__.py
thermocouples/types/type_b_class.py
thermocouples/types/type_e_class.py
thermocouples/types/type_j_class.py
thermocouples/types/type_k_class.py
thermocouples/types/type_n_class.py
thermocouples/types/type_r_class.py
thermocouples/types/type_s_class.py
thermocouples/types/type_t_class.py
thermocouples-2.1.2.dist-info/licenses/LICENSE
thermocouples-2.1.2.dist-info/METADATA
thermocouples-2.1.2.dist-info/WHEEL
thermocouples-2.1.2.dist-info/top_level.txt
thermocouples-2.1.2.dist-info/RECORD
