Metadata-Version: 2.4
Name: thermocouples
Version: 2.1.2
Summary: Clean object-oriented thermocouple library with simplified API and hidden implementation details for professional use
Author: RogerGdot
License: MIT
Project-URL: Homepage, https://github.com/RogerGdot/thermocouples
Project-URL: Documentation, https://github.com/RogerGdot/thermocouples#readme
Project-URL: Repository, https://github.com/RogerGdot/thermocouples.git
Project-URL: Bug Tracker, https://github.com/RogerGdot/thermocouples/issues
Project-URL: Source Code, https://github.com/RogerGdot/thermocouples
Project-URL: Changelog, https://github.com/RogerGdot/thermocouples/releases
Keywords: thermocouple,temperature,voltage,nist,measurement,sensor,instrumentation,seebeck,cold-junction,oop,abstract-base-class,factory-pattern,polynomials
Classifier: Development Status :: 5 - Production/Stable
Classifier: Intended Audience :: Science/Research
Classifier: Intended Audience :: Manufacturing
Classifier: Intended Audience :: Developers
Classifier: Operating System :: OS Independent
Classifier: Programming Language :: Python :: 3
Classifier: Programming Language :: Python :: 3.9
Classifier: Programming Language :: Python :: 3.10
Classifier: Programming Language :: Python :: 3.11
Classifier: Programming Language :: Python :: 3.12
Classifier: Programming Language :: Python :: 3.13
Classifier: Topic :: Scientific/Engineering
Classifier: Topic :: Scientific/Engineering :: Physics
Classifier: Topic :: Scientific/Engineering :: Chemistry
Classifier: Topic :: Software Development :: Libraries :: Python Modules
Classifier: Typing :: Typed
Requires-Python: >=3.9
License-File: LICENSE
Provides-Extra: dev
Requires-Dist: pytest>=7.0; extra == "dev"
Requires-Dist: build>=0.10.0; extra == "dev"
Requires-Dist: twine>=4.0.0; extra == "dev"
Dynamic: license-file
